dpmg/__init__.py
dpmg/main.py
dpmg-0.1.0.dist-info/METADATA
dpmg-0.1.0.dist-info/WHEEL
dpmg-0.1.0.dist-info/top_level.txt
dpmg-0.1.0.dist-info/RECORD
